{
    "PingInterceptor": 0,
    "PingCDIBean": 0,
    "PingServlet2PDF": 0,
    "TradeDirect": 0,
    "PingServlet2DB": 0,
    "TradeBuildDB": 1,
    "AccountDataBean": 1,
    "AccountProfileDataBean": 1,
    "TradeServletAction": 2,
    "TradeAppServlet": 2,
    "OrdersAlertFilter": 2,
    "TradeSLSBBean": 2,
    "TradeAction": 2,
    "MarketSummaryWebSocket": 2,
    "TradeScenarioServlet": 2,
    "PingServlet2SessionLocal": 2,
    "PingServletCDIBeanManagerViaCDICurrent": 2,
    "PingServlet2Servlet": 3,
    "PingServlet2Include": 3,
    "PingServlet2ServletRcv": 3,
    "PingServlet2IncludeRcv": 3,
    "PingBean": 3,
    "TradeConfigServlet": 3,
    "TradeConfig": 4,
    "Log": 4,
    "TradeWebContextListener": 4,
    "KeyBlock::KeyBlockIterator": 5,
    "KeyBlock": 5,
    "KeySequenceDirect": 5,
    "PingServletCDIBeanManagerViaJNDI": 6,
    "PingJDBCRead2JSP": 6,
    "JsonEncoder": 6,
    "PingWebSocketJson": 6,
    "JsonMessage": 6,
    "JsonDecoder": 6,
    "JSFLoginFilter": 6,
    "FinancialUtils": 7,
    "QuoteDataBean": 7,
    "ActionMessage": 7,
    "ActionDecoder": 7,
    "PingServletCDI": 7,
    "PingEJBLocal": 7,
    "PingEJBLocalDecorator": 7,
    "TradeActionProducer": 7,
    "ExternalContextProducer": 7,
    "QuoteJSF": 7,
    "QuoteData": 7,
    "DTStreamer3MDB": 7,
    "TimerStat": 7,
    "RecentStockChangeList": 7,
    "PingCDIJSFBean": 7,
    "RunStatsDataBean": 7,
    "PingJDBCRead": 7,
    "MarketSummaryDataBean": 7,
    "PingServlet2Jsp": 7,
    "MarketSummarySingleton": 7,
    "OrderDataBean": 8,
    "HoldingDataBean": 8,
    "PingUpgradeServlet": 8,
    "PingJDBCWrite": 8,
    "MDBStats": 8
}